AUTHORS
CHANGELOG.txt
DESCRIPTION
LICENSE
MANIFEST.in
README.rst
setup.cfg
setup.py
django_units.egg-info/PKG-INFO
django_units.egg-info/SOURCES.txt
django_units.egg-info/dependency_links.txt
django_units.egg-info/requires.txt
django_units.egg-info/top_level.txt
units/__init__.py
units/constants.py
units/exceptions.py
units/models.py
units/settings.py
units/utils.py
units/forms/__init__.py
units/forms/mixins.py
units/templatetags/.units_tags.py.swo
units/templatetags/__init__.py
units/templatetags/units_tags.py
units/tests/.coveragerc
units/tests/__init__.py
units/tests/factories.py
units/tests/forms_mixins_tests.py
units/tests/runtests.py
units/tests/south_settings.py
units/tests/test_settings.py
units/tests/units_tags_tests.py
units/tests/urls.py
units/tests/utils_tests.py
units/tests/test_app/__init__.py
units/tests/test_app/models.py