Metadata-Version: 1.0
Name: django-units
Version: 0.2.1
Summary: A Django app to convert units between different systems
